MANIFEST.in
README.md
export2graphlan.py
setup.py
export2graphlan.egg-info/PKG-INFO
export2graphlan.egg-info/SOURCES.txt
export2graphlan.egg-info/dependency_links.txt
export2graphlan.egg-info/requires.txt
export2graphlan.egg-info/top_level.txt