Metadata-Version: 2.1
Name: export2graphlan
Version: 0.22
Summary: export2graphlan is a conversion software tool for producing both annotation and tree file for GraPhlAn
Home-page: http://github.com/segatalab/export2graphlan
Author: Francesco Asnicar
Author-email: f.asnicar@unitn.it
License: UNKNOWN
Platform: UNKNOWN
